{
    "version": 3,
    "vendor": {
        "conan": {}
    },
    "cmakeMinimumRequired": {
        "major": 3,
        "minor": 15,
        "patch": 0
    },
    "configurePresets": [
        {
            "name": "conan-release",
            "displayName": "'conan-release' config",
            "description": "'conan-release' configure using 'Unix Makefiles' generator",
            "generator": "Unix Makefiles",
            "cacheVariables": {
                "CMAKE_POLICY_DEFAULT_CMP0091": "NEW",
                "CMAKE_BUILD_TYPE": "Release"
            },
            "toolchainFile": "/home/walde/workspace/cxx/stlplus3/trunk/build/release-clang/conan_toolchain.cmake",
            "binaryDir": "/home/walde/workspace/cxx/stlplus3/trunk/build/release-clang"
        }
    ],
    "buildPresets": [
        {
            "name": "conan-release",
            "configurePreset": "conan-release",
            "jobs": 16
        }
    ],
    "testPresets": [
        {
            "name": "conan-release",
            "configurePreset": "conan-release"
        }
    ]
}